lumos/__init__.py
lumos/__main__.py
lumos/cli.py
lumos/generator.py
lumos/lumos.py
pylumos-0.0.3.dist-info/LICENSE
pylumos-0.0.3.dist-info/METADATA
pylumos-0.0.3.dist-info/WHEEL
pylumos-0.0.3.dist-info/entry_points.txt
pylumos-0.0.3.dist-info/top_level.txt
pylumos-0.0.3.dist-info/RECORD
